cosymlib-0.11.1.data/scripts/mosym
cosymlib-0.11.1.data/scripts/shape
cosymlib-0.11.1.data/scripts/shape_classic
cosymlib-0.11.1.data/scripts/esym
cosymlib-0.11.1.data/scripts/cchir
cosymlib-0.11.1.data/scripts/shape_map
cosymlib-0.11.1.data/scripts/gsym
cosymlib-0.11.1.data/scripts/cosym
cosymlib/__init__.py
cosymlib/utils.py
cosymlib/tools/__init__.py
cosymlib/tools/periodic_table.yaml
cosymlib/shape/maps.py
cosymlib/shape/tools.py
cosymlib/shape/__init__.py
cosymlib/shape/shp.cpython-36m-darwin.so
cosymlib/shape/ideal_structures_center.yaml
cosymlib/file_io/tools.py
cosymlib/file_io/__init__.py
cosymlib/file_io/classic_inputs.py
cosymlib/file_io/errors.py
cosymlib/simulation/__init__.py
cosymlib/symmetry/tools.py
cosymlib/symmetry/__init__.py
cosymlib/.dylibs/libgfortran.5.dylib
cosymlib/.dylibs/libquadmath.0.dylib
cosymlib/.dylibs/libgcc_s.1.1.dylib
cosymlib/gui/__init__.py
cosymlib/molecule/__init__.py
cosymlib/molecule/electronic_structure/protoelectronic_structure.py
cosymlib/molecule/electronic_structure/__init__.py
cosymlib/molecule/geometry/__init__.py
cosymlib-0.11.1.dist-info/RECORD
cosymlib-0.11.1.dist-info/LICENSE
cosymlib-0.11.1.dist-info/WHEEL
cosymlib-0.11.1.dist-info/top_level.txt
cosymlib-0.11.1.dist-info/METADATA
