Metadata-Version: 2.1
Name: cosymlib
Version: 0.11.1
Summary: Continuous measures of shape and symmetry
Home-page: https://github.com/GrupEstructuraElectronicaSimetria/cosymlib
Author: Efrem Bernuz
Author-email: komuisan@gmail.com
License: UNKNOWN
Platform: UNKNOWN
Classifier: Programming Language :: Python
Classifier: License :: OSI Approved :: MIT License
License-File: LICENSE
Requires-Dist: numpy
Requires-Dist: matplotlib
Requires-Dist: symgroupy
Requires-Dist: wfnsympy
Requires-Dist: PyYAML
Requires-Dist: huckelpy
Requires-Dist: pointgroup
